LICENSE
README.md
setup.py
kashpy/__init__.py
kashpy/kash.py
kashpy.egg-info/PKG-INFO
kashpy.egg-info/SOURCES.txt
kashpy.egg-info/dependency_links.txt
kashpy.egg-info/requires.txt
kashpy.egg-info/top_level.txt
test/test_kash.py