Metadata-Version: 2.1
Name: kashpy
Version: 0.0.12
Summary: A Kafka Shell based on Python
Home-page: https://github.com/xdgrulez/kash.py
Author: Ralph M. Debusmann
Author-email: matthias.debusmann@gmail.com
License: Apache License 2.0
Platform: UNKNOWN
Classifier: Development Status :: 3 - Alpha
Classifier: Intended Audience :: Developers
Classifier: License :: OSI Approved :: Apache Software License
Classifier: Programming Language :: Python :: 3.6
Classifier: Topic :: Software Development :: Libraries :: Python Modules
License-File: LICENSE
